cartha_cli/__init__.py
cartha_cli/bt.py
cartha_cli/config.py
cartha_cli/display.py
cartha_cli/eth712.py
cartha_cli/main.py
cartha_cli/pair.py
cartha_cli/utils.py
cartha_cli/verifier.py
cartha_cli/wallet.py
cartha_cli/commands/__init__.py
cartha_cli/commands/common.py
cartha_cli/commands/config.py
cartha_cli/commands/health.py
cartha_cli/commands/help.py
cartha_cli/commands/miner_password.py
cartha_cli/commands/miner_status.py
cartha_cli/commands/pair_status.py
cartha_cli/commands/pools.py
cartha_cli/commands/prove_lock.py
cartha_cli/commands/register.py
cartha_cli/commands/shared_options.py
cartha_cli/commands/version.py
cartha_cli/testnet/README.md
cartha_cli/testnet/__init__.py
cartha_cli/testnet/pool_ids.py
cartha_cli-1.0.7.dist-info/METADATA
cartha_cli-1.0.7.dist-info/WHEEL
cartha_cli-1.0.7.dist-info/entry_points.txt
cartha_cli-1.0.7.dist-info/licenses/LICENSE
cartha_cli-1.0.7.dist-info/RECORD
