Metadata-Version: 2.4
Name: cartha-cli
Version: 1.0.7
Summary: CLI utilities for Cartha subnet miners.
Project-URL: Homepage, https://cartha.finance
Project-URL: Repository, https://github.com/General-Tao-Ventures/cartha-cli
Project-URL: Documentation, https://github.com/General-Tao-Ventures/cartha-cli#readme
Author: Cartha Contributors
License-Expression: MIT
License-File: LICENSE
Keywords: 0xmarkets,bittensor,cartha,cli,mining,subnet
Classifier: Development Status :: 4 - Beta
Classifier: Environment :: Console
Classifier: Intended Audience :: Developers
Classifier: License :: OSI Approved :: MIT License
Classifier: Operating System :: OS Independent
Classifier: Programming Language :: Python :: 3
Classifier: Programming Language :: Python :: 3.11
Classifier: Topic :: Software Development :: Libraries :: Python Modules
Requires-Python: <3.12,>=3.11
Requires-Dist: bittensor<10,>=9.12.2
Requires-Dist: eth-account<0.11,>=0.10
Requires-Dist: pydantic-settings<3,>=2.6
Requires-Dist: pydantic<3,>=2.6
Requires-Dist: python-dotenv>=1.0
Requires-Dist: requests>=2.32
Requires-Dist: torch<3,>=2.2
Requires-Dist: typer[all]>=0.12
Requires-Dist: web3<7,>=6.11
Provides-Extra: dev
Requires-Dist: pytest>=8.2; extra == 'dev'
